telealert/__init__.py
telealert/main.py
telealert-1.1.0.dist-info/licenses/LICENSE
telealert-1.1.0.dist-info/METADATA
telealert-1.1.0.dist-info/WHEEL
telealert-1.1.0.dist-info/top_level.txt
telealert-1.1.0.dist-info/RECORD
