Metadata-Version: 2.4
Name: telealert
Version: 1.1.0
Summary: Async Telegram alert/notification library
Author-email: Husniddin <agzamovhusniddin73@gmail.com>
License: Copyright (c) 2025 telealert
Classifier: Programming Language :: Python :: 3
Classifier: License :: OSI Approved :: MIT License
Classifier: Operating System :: OS Independent
Requires-Python: >=3.10
License-File: LICENSE
Requires-Dist: aiogram>=3.10.0
Dynamic: license-file
